[
  {
    "category": "Gratitude Journal Prompts",
    "prompts": [
      "Name the one thing you are most grateful for in your life at this moment.",
      "Which people in your life are you most grateful for.",
      "Write about something that made you smile today.",
      "When were you last surprised?",
      "What is the most exhilarating thing that has happened to you this year?",
      "Name a challenge you have overcome and how it helped you to grow.",
      "How can you show gratitude more?"
    ]
  },
  {
    "category": "Lists",
    "prompts": [
      "What 5 things are you grateful for this week?",
      "Write about 5 amazing childhood memories you are grateful for.",
      "List your fitness and health goals.",
      "What are 3 things that have happened to you which were difficult but you are now grateful for the experience?",
      "Places you have travelled",
      "Places you want to travel in the future",
      "Books you want to read",
      "Things you have learned in life",
      "Movies or TV series you want to watch",
      "Experiences you want to have with your partner",
      "Experiences you want to create with your children",
      "Family traditions",
      "Self-improvement projects you want to do",
      "Career advancements or new types of careers you would like to try",
      "What your life might look like at different points in your future",
      "Places you have lived",
      "Places you would like to live",
      "Ways you can make the world a better place",
      "How your life would improve if you worked on your personal health this year",
      "Ways you can de-stress every day",
      "Favorite songs",
      "Things you are grateful for right at this moment",
      "People you see every day and ONE good thing about them",
      "Your favourite quotes or sayings"
    ]
  },
  {
    "category": "Health and Wellness Prompts",
    "prompts": [
      "Keep a food tracker for the day.",
      "Make a meal planner. Head to our meal planning post for ideas.",
      "Write down your measurements and weight so you can compare later.",
      "What is your favourite way to exercise?",
      "Did you make healthy choices today?",
      "Name one simple way you can take a step to be healthier.",
      "How can you make activity part of your normal routine?",
      "What is your favourite food?",
      "Are you feeling stressed?",
      "Keep a mood or habit tracker to help understand your mental health.",
      "Think about what triggers your stress, emotions, poor eating habits.",
      "What is a bad habit you would like to change? What actionable steps can you take to make it happen?"
    ]
  },
  {
    "category": "Goal and Aspirations Prompts",
    "prompts": [
      "What are your top 10 goals?",
      "Write down actionable steps to help you reach a goal.",
      "What is your 1-year goal?",
      "What is your 5-year goal?",
      "What is your 10-year goal?",
      "If you could start life again, would you? What would you change?",
      "Who is someone that inspires you and why?",
      "Is there a hobby you would like to start?",
      "Name a skill you would love to learn.",
      "What kind of person do you aspire to be?"
    ]
  },
  {
    "category": "Journal Prompts for Memories",
    "prompts": [
      "What is your favourite childhood memory?",
      "Write about the first memory you have.",
      "Describe your childhood.",
      "Do you have an embarrassing moment that still makes you cringe?",
      "Which was your best birthday ever and why?",
      "What was a hobby you loved as a kid?",
      "Write about your favourite memory with your parents.",
      "What was your favourite toy?",
      "What is your best memory with some of the special people in your life?",
      "What is a memory that always makes you smile?"
    ]
  },
  {
    "category": "Travel Prompts",
    "prompts": [
      "Where is the place you would like to visit the most?",
      "What has been your best trip so far?",
      "Who is the person you would like to travel with the most and why?",
      "If you could go back in time, where would you go?",
      "Describe your dream vacation.",
      "Write about a road trip you would love to take.",
      "How does seeing somewhere new make you feel?",
      "What is a food you would love to try from a different country?",
      "What is the worst vacation you have ever had?",
      "Name 10 places you would love to see."
    ]
  },
  {
    "category": "Daily Prompts",
    "prompts": [
      "Write your day in bullet points.",
      "Do your current friendships and relationships bring joy to you?",
      "What is your biggest concern right now?",
      "Do you think you are a positive or negative person?",
      "What are your best qualities?",
      "Could you be a better friend?",
      "Could you be a better partner/wife/husband/mother/father/daughter or Son?",
      "Write about your top five personal strengths.",
      "What things change your mood from positive to negative?",
      "Make a list of 10 affirmations that will lift your mood.",
      "Do you have a morning routine? Can it be improved?",
      "How are you feeling today?"
    ]
  },
  {
    "category": "Simple Journal Prompts",
    "prompts": [
      "What are your plans for this weekend?",
      "Write 5 affirmations for when you are feeling low.",
      "What is the best book you have read recently?",
      "How have you grown this year?",
      "What are the most important life lessons you have learned?",
      "Having trouble sleeping? What's keeping you up?",
      "What is the last dream you remember?",
      "Name the three biggest priorities in your life right now.",
      "What are your biggest fears?",
      "Do you have a fear that is stopping you from achieving your goals?",
      "Name three challenges…. and three ways to overcome them.",
      "Write down your ultimate way to relax.",
      "What would you do if you were granted three wishes?",
      "How about if you were given five wishes?",
      "Name three bad habits you would like to change.",
      "What was the last show you went to?",
      "Do you have a secret talent you are hiding?",
      "Add some more items to your bucket list…if you don't have a bucket list, start one.",
      "What is your biggest regret?",
      "Think about someone you really love. Write about the person that came to mind.",
      "List the best 10 moments of your life so far."
    ]
  },
  {
    "category": "Beginners",
    "prompts": [
      "How do I feel?",
      "How do I want to feel (today)",
      "What do I need (most today)?",
      "What am I grateful for? (List at least 5 things and if you want to expand it, you can also say why you're grateful for each item on your list.)",
      "What was my biggest lesson or achievement today/this week/this month?",
      "The things that bring me the most joy in my life are…",
      "The people in my life who bring me the most joy are…",
      "I feel happiest when…",
      "What do I feel happy about right now?",
      "What am I excited about today?",
      "What am I looking forward to?",
      "How can I experience more joy, happiness and/or peace in my life?",
      "What changes do I need to feel healthier, happier and more fulfilled?",
      "What is my happiest memory from today/this week/this month?",
      "I feel most at peace/relaxed when…",
      "I feel most loved when…",
      "When I am alone I feel…",
      "When I am surrounded by people I feel…",
      "I want/need to forgive…",
      "What is currently my biggest fear, worry or concern?",
      "What is the main cause of stress in my life?",
      "How can I reduce the stress in my life?",
      "What is most important to me right now?",
      "What do I feel guilty about right now?",
      "What do I feel sad or upset about right now?",
      "What do I feel angry about right now?",
      "Who or what do I feel resentful towards/about right now?",
      "What do I feel disappointed about right now?",
      "What am I dreading?",
      "If I could change one thing about my present life, what would it be?",
      "I need to tell the truth about/be honest with…",
      "What do I feel I am currently lacking in my life? What do I need more of?",
      "Where do I currently have too much excess in my life? What do I need less of right now?",
      "Who or what do I need to let go of or at least distance myself from?",
      "Where or with who do I need stronger personal boundaries?"
    ]
  },
  {
    "category": "Self Discovery",
    "prompts": [
      "What am I most proud of?",
      "What have I achieved today?",
      "What would I tell my future self?",
      "If I could do anything, what would it be?",
      "What are 7 things that make me happy?",
      "What would my perfect day look like?",
      "What are my strengths?",
      "What are my weaknesses?",
      "What am I afraid of?",
      "Where do I want to be in the next 5 years?",
      "What do I need more of in my life?",
      "What do I need less of?",
      "How am I feeling right now?",
      "What do I love about myself?",
      "What drains my energy?",
      "Who or what inspires me the most?",
      "What am I thankful for?",
      "What do I feel strongly about?",
      "How do I take care of myself?",
      "What are my three biggest goals?",
      "My top 5 quotes.",
      "What motivates me?",
      "Describe yourself in 10 words.",
      "My top 10 favourite places to go?",
      "What is something I'll never forget?",
      "What is my saddest memory?",
      "What is my best memory?",
      "What are my daily habits?",
      "What is holding me back from changing?",
      "What am I passionate about?",
      "I deserve love because…",
      "I deserve kindness because…",
      "I deserve friendship because…",
      "My top 5 daily mantras/ affirmations?",
      "I forgive myself for…",
      "Who are my favourite 3 people in the world?",
      "Some advice you would give to a best friend.",
      "List One challenge I have overcome and how I did it.",
      "What do I do for self-care?",
      "List all of my accomplishments.",
      "What makes me feel truly alive?",
      "What do I want my legacy to be?",
      "How can I show myself more love and affection?",
      "What do I need most to heal right now?",
      "What brings me joy?",
      "What makes me feel happy?",
      "What makes me feel excited?",
      "How do I add value to the world?",
      "What annoys me?",
      "What does my dream life look like?"
    ]
  },
  {
    "category": "Journal Prompts For Your Personality, Likes, Dislikes",
    "prompts": [
      "What are the 3 things you like most about yourself?",
      "If you could change one thing about yourself what would it be?",
      "What are your best traits?",
      "What are your worst traits?",
      "What is the biggest compliment you have ever received?",
      "What do you need to make you feel safe?",
      "Where is your safe place?",
      "What do you worry about?",
      "Do you worry too much? How can you deal with this?",
      "What is your favourite song? What does it mean to you?",
      "What is your greatest accomplishment?",
      "What are you most thankful for?",
      "What would your ideal day be?",
      "Who is your biggest inspiration and why?",
      "How would you describe yourself to a stranger?",
      "How would you want other people to describe you?",
      "What life lessons have books taught you?",
      "Which fictional character would you most like to be?",
      "What are your strengths?",
      "What are your weaknesses?",
      "What countries have you travelled to?",
      "What lessons have you learned from travelling?",
      "What is your favourite place?",
      "Is there anything that has changed your outlook on life?",
      "Who would you most love to meet?",
      "What habit would you most like to break?",
      "What excites you?",
      "What place do you consider your home?",
      "Are you good at decision making? How could you improve?",
      "Are you an organised person?",
      "Is there a part of your life that you wish was more organised?",
      "What is the most important thing to enable you to live an authentic life?",
      "What matters to you the most?",
      "What doesn't matter to you?",
      "What are your priorities?",
      "What keeps you motivated?",
      "What makes you proud?",
      "What are 3 facts about you that not many people know?",
      "How do you focus?",
      "Could you be more focused? How will you achieve this?",
      "What are you looking forward to?",
      "How would you change the world?",
      "What have you recently learned about yourself?",
      "What is your favourite time of day and why?",
      "What one thing can you not give up?",
      "What is the best gift somebody could give you?",
      "What rules or standards do you live by?",
      "What could you easily live without?",
      "What is your reaction when you don't get what you want?",
      "Do you have self-control or is it something you need to work on?",
      "How do you deal with obstacles that get in your way?",
      "Do you deal well with rejection?",
      "If you could be any animal what would it be and why?",
      "Do you always tell the truth?",
      "Are you able to forgive others?",
      "Are you able to forgive yourself?",
      "Do you have leadership qualities or are you strictly a follower?",
      "Have you managed to overcome a fear?",
      "When was the last time you were creative?",
      "Do have problems releasing your creative side? Why do you think this is?",
      "Do you find it easy to ask for help?",
      "Who would play you in the film about your life?",
      "Can you keep a secret?",
      "Do you dress for yourself or to impress other people?",
      "What changes could you make to improve your health?",
      "What are you passionate about?",
      "Do you cope well when faced with a challenge?",
      "Are you a leader or a follower?",
      "Are you a confident person or do you find yourself doubting your abilities?",
      "When was the last time you did something spontaneous? How did it make you feel?",
      "How much do you love yourself right now?",
      "What makes you uncomfortable?",
      "Do you have any small rituals that give you comfort? What are they?",
      "Are you a patient person?",
      "Do you find yourself apologising a lot? Why do you think you do this?",
      "Do you have self-discipline? If this is a problem for you, what can you do to improve?",
      "What does your work mean to you?",
      "What do you daydream about?",
      "What is your biggest failure?",
      "What is the biggest decision you've ever had to make?",
      "What makes you unique?",
      "What was the last thing you celebrated?",
      "What are your beliefs, do you always stay true to them?",
      "Are you an introvert or an extrovert?",
      "What's the most difficult choice you ever had to make?",
      "What would you like to do more of?",
      "What would you like to do less of?",
      "How is the pace of your life? Is it too fast or too slow for you?",
      "Are you good at problem-solving?",
      "Are you kind to yourself?",
      "Do you find it easy to feel empathy towards others?",
      "Do you feel that you are a good communicator?",
      "What are your pet peeves?",
      "Do you have a strong work ethic?",
      "Do you have spiritual beliefs that help guide you?",
      "What quote inspires you?",
      "If you could sum your life up in one word what would it be?",
      "Do you ever break the rules?",
      "Are there parts of your life that you find distracting?",
      "Do you take the time to reflect on what is happening in your life?",
      "How do you feel outside of your comfort zone? Do you see this as a positive or a negative thing?",
      "Do you find your life fulfilling?",
      "Are you putting any parts of your life on hold? If so why?",
      "What makes you feel young?",
      "Do you work well under pressure?",
      "What makes your life worthwhile?",
      "What 5 words would you use to describe yourself?",
      "Has anything changed your outlook on life?",
      "Do you easily give up on things? Why is this?",
      "Can you admit when you are in the wrong?",
      "What do you need to make more time for?",
      "Are you good at organising your time? How could you improve?",
      "Do you display self-destructive behaviour?",
      "What makes your life more difficult?",
      "What cause do you feel strongly about? How can you help?",
      "Do you react well in a crisis?",
      "What is your most treasured possession and why?",
      "What can't you live without?",
      "Do you have fears of abandonment? Why could this be?"
    ]
  },
  {
    "category": "Journal Prompts For Your Thoughts, Feelings, Emotions",
    "prompts": [
      "What makes you feel at peace?",
      "What would make you happy right now?",
      "How do you feel right at this moment?",
      "What is causing you stress right now?",
      "What makes you feel alive?",
      "What makes you sad?",
      "What do you need to let go of?",
      "What makes you angry? How do you deal with the anger?",
      "What cheers you up when you are feeling down?",
      "Do you always need to be in control? How do you feel when you have no control over a situation?",
      "Do you deal well with change?",
      "How do you cope with stressful situations?",
      "Do you believe crying is a healthy outlet for negative emotions? What makes you cry?",
      "When was the last time you cried?",
      "What was the happiest moment of your life?",
      "If you ran away where would you go?",
      "What makes you laugh?",
      "Are you easily embarrassed? Why do you think this is?",
      "What is the most embarrassing thing that's ever happened to you?",
      "What was the last thing to surprise you?",
      "Do you hide your emotions? If so, why?",
      "How do you deal with negative comments?",
      "Who or what keeps you calm?",
      "Do you carry emotional baggage? How can you deal with this?",
      "Are your emotions unbalanced? How can you address this?",
      "Are you easily frustrated? What is that frustrates you?",
      "Do you find yourself feeling guilt over things that are beyond your control?",
      "Do you ever feel envious? Do you feel that this healthy?",
      "What can you do to feel more content with what you have?",
      "Have you ever grieved for a loved one? How did you process this grief?",
      "What do you miss the most?",
      "What do you need the most in life?",
      "What makes you feel better?",
      "What one thing always makes you smile?",
      "What has made you smile today?",
      "Do your emotions motivate you? Is this in a positive or negative way?",
      "What causes you to be anxious?",
      "What makes you joyful?",
      "Do you have mood swings? What do you think causes them?",
      "Who do you call to cheer you up?",
      "Do you find it easy to talk about your feelings, or do you bottle things up?",
      "Are you often disappointed with life?",
      "Do the changing seasons affect your emotions? Why do you think that is?",
      "What do you like to do to relax and wind down?",
      "Are you easily overwhelmed?",
      "Is there anything in your life that makes you ashamed?",
      "Are you a nervous person? Why do you think that is?",
      "What makes you nervous?",
      "Do you feel you lack courage? What do you wish you had the courage to do?",
      "What emotion do you wish you didn't feel?",
      "What makes you feel powerful?",
      "How do you deal with emotional pain?",
      "What do you love about life?",
      "Do you find it difficult to control your temper?",
      "What helps you heal?",
      "What are the little things that make you happy?",
      "If you could choose to have any emotion right now what would it be?",
      "Do you ever feel numb? What causes this?",
      "What emotion do you feel most often?",
      "Do you like surprises or do they unsettle you?",
      "What makes you feel free?",
      "Would you say you are an optimistic person?",
      "Do you ever feel inferior? Why is this?",
      "How does uncertainty make you feel?",
      "Are you easily annoyed, what annoys you?",
      "What is your biggest fear? Why do you think you are afraid?",
      "Do you let this fear rule your life or do you deal with it in a healthy way?"
    ]
  },
  {
    "category": "Journal Prompts For Your Past",
    "prompts": [
      "What one thing would you change about your childhood",
      "If you could go back to when you were a child, what would you say to yourself?",
      "What were the good things you remember from your childhood?",
      "What is your biggest regret?",
      "What was the best birthday you ever had?",
      "What did you want to be when you were younger?",
      "What is your happiest memory?",
      "What family traditions did you have as a child?",
      "Where were you, 10 years, 5 years, and 1 year ago?",
      "What mistakes have you learned from in the past?",
      "What time in your life do you always want to remember?",
      "What song holds special memories for you?",
      "What is your saddest memory?",
      "What has been the most difficult time in your life?",
      "If you could relive one day over again, what day would it be?",
      "What has been the best year in your life?",
      "Who was your biggest influence growing up?",
      "Has your family life changed since you were a child?",
      "What was your favourite thing to do as a child?",
      "Have you said anything in the past that you wish you hadn't?",
      "Did you enjoy school? What life lessons did you learn from your time there?",
      "Did you find it easy to get along with your peers when you were growing up?",
      "Did you ever experience bullying? How did you deal with this?",
      "What from your past do you wish you could do over?",
      "Have any past experiences shaped the fears and anxieties you have today?",
      "What has been the most challenging part of your life to date?",
      "During your childhood did you ever feel let down by an adult?",
      "What were you doing this time last year?",
      "Did you ever witness anything in the past that you wish you hadn't?",
      "What smell brings about good memories?",
      "What was your favourite family vacation?",
      "Were there secrets in your family? How did that affect you?",
      "Does the way you were brought up influence the way you (will) bring up your children?",
      "If you have siblings, how is your relationship with them? Has it change now that you are adults?"
    ]
  },
  {
    "category": "Journal Prompts For Your Wishes, Hopes, Dreams, And Future",
    "prompts": [
      "What do you believe you deserve in life?",
      "What one thing have you always wished for?",
      "What skill have you always wanted to have?",
      "What would you like to achieve in the next year?",
      "What new hobbies would you like to try?",
      "Where would you like to travel?",
      "How could your life be better?",
      "Is anything holding you back?",
      "What are your goals for this month?",
      "Is your life what you imagined it would be?",
      "What small change would you like to make to your life?",
      "What big change would you like to make to your life?",
      "What is your dream job?",
      "What is your vision for the future? How will you get there?",
      "What gives you hope?",
      "What do you fear most about the future?",
      "Does growing old scare you?",
      "You have decided to emigrate, where are you going to live?",
      "What do you want most out of life?",
      "What one thing could you do today to help you achieve your goals?",
      "What could you do to improve your finances in the future?",
      "Is anything holding you back from achieving your goals? How can you deal with it?",
      "Do you embrace the “new”?",
      "Do you believe you deserve good things to happen to you? If not, why?",
      "What new thing do you want to try in the next year?",
      "What in your life are you still trying to figure out?",
      "What makes you happy about your life right now?",
      "What makes you sad about your life right now?",
      "Are you satisfied with life?",
      "What difference would you make to the world?",
      "What do you want your legacy to be?",
      "What gifts to you want to share with the world?",
      "Do you have a dream life? What is it like?",
      "What do you think your mission is in life?",
      "Do you find it easy to commit to getting want you want in life?",
      "Are your expectations of yourself too high?",
      "Do you find it easy to follow through on a plan you have made?",
      "What would give your life more meaning?",
      "What are your career goals?",
      "Where would you like to live in the future?",
      "What are your personal goals?"
    ]
  },
  {
    "category": "Self Care: Journal Prompts For Your Relationships",
    "prompts": [
      "What does love mean to you?",
      "What qualities do you admire most in others?",
      "Who do you love and why?",
      "Who would you like to reconnect with and why?",
      "What do you look for in a friend?",
      "Who do you trust?",
      "Who makes your life better?",
      "How do you help your friends and loved ones?",
      "What time in your life did you need a friend most?",
      "How do you show people that you love them?",
      "Describe your best friend. What do you have in common? What makes the friendship work?",
      "What's the best advice you could give to others?",
      "How do you show appreciation to others?",
      "How do you deal with negative people?",
      "How do you deal with people who have different opinions and beliefs from you?",
      "Are you willing to forgive others?",
      "Done you prefer a small or large group of friends?",
      "Are you ever misunderstood by people?",
      "You receive exciting news, who do you tell first?",
      "What is the best advice you have ever been given?",
      "Think about your past romantic relationships. What lessons did you learn from them? What did each person bring to your life?",
      "Have you ever had your heart broken?",
      "What is your perfect date?",
      "How do you deal with confrontation?",
      "What qualities do you like least in others?",
      "Do you feel that you have the support of friends and family?",
      "Do you feel that you are valued by others?",
      "What do you want other people to know about you?",
      "Who do you look up to?",
      "Who do you love unconditionally?",
      "Who has your back?",
      "What makes you lovable?",
      "How comfortable are you meeting new people?",
      "What is the nicest thing anyone has ever done for you?",
      "Do you care what others think of you?",
      "Are you easily influenced by others?",
      "How is your relationship with your parents?",
      "Do you believe in soul mates?",
      "What are the 3 most important things in a relationship?",
      "Can you accept people for who they are?",
      "Do you feel accepted?",
      "Is there a relationship in your life you would like to change? How would you change it?",
      "How do you fit into your family? What is your role?",
      "Your family is always the people you are related to. Which non relatives do you consider family?",
      "Do you have any toxic friendships in your life? How can you deal with this?",
      "Do you find it easy to apologise to others?",
      "Are you a good listener?",
      "Have your views on love changed since you were a teenager? If so, why?",
      "Are you a secretive person? Do you find it easy to confide in other people?",
      "Who are you closest to in your family and why?",
      "Who knows you the best?",
      "Do you share the same values as other members of your family? Is there a big difference between your values and those of the older members of your family?",
      "Are you attracted to the same personality type as yourself or the opposite?",
      "What one thing do you wish someone would say to you?",
      "Do you make friends easily?",
      "Who did you last spend quality time with. Why do you think you connect well with that person?",
      "Do you think you are fairly judged by others?",
      "Is there someone in your life you should be spending more time with?",
      "Is there someone you should be spending less time with?",
      "Have you ever loved someone who didn't love you back? How did that make you feel?",
      "Have you ever betrayed a friend?",
      "Have you ever been betrayed by a friend?",
      "Have you ever felt controlled by another person?",
      "Who, in your life makes you feel special?",
      "Who can you share comfortable silences with?",
      "Who are you most like in your family?",
      "Do you think people look up to you?",
      "Who can calm you down?",
      "Who are you not afraid to be yourself with?",
      "Do you think it is important to be honest with people even if that honesty causes pain?",
      "Do you have friends who have different backgrounds to you? Do you feel this is important?",
      "Who would you turn to in a crisis?",
      "Have you ever been afraid of another person? How did you deal with this?",
      "Do you ever feel sad about people you have lost touch with who were once important to you?",
      "How do you think your work colleagues feel about you?",
      "How do you feel about them? Do you have good working relationships?",
      "Do you feel that you need more encouragement from others?",
      "Can you communicate well in a relationship? Do you talk out your problems?",
      "Have you ever lied or cheated in a relationship? Did you come clean? Do you regret it now?"
    ]
  },
  {
    "category": "Journal Prompts For Health and Well Being",
    "prompts": [
      "How do you feel about your body? Would you change anything?",
      "How could you take better care of your mental health?",
      "What changes could you make to improve your physical health?",
      "Are you getting enough sleep? If not, why do you think that is?",
      "Do you lack energy? If so, what is causing this?",
      "Do you get enough exercise?",
      "Are you comfortable looking in a mirror?",
      "How do you feel about others seeing your body, for example at the beach?",
      "Do you worry about getting ill?",
      "Are you afraid of death?",
      "Are you self conscious?",
      "What are your insecurities?",
      "How in tune out you with your body? Do you know when it's time to rest?",
      "Does stress affect your body? How can you address this?",
      "What is your favourite part of your body?",
      "Do you have a good relationship with food?",
      "Do you have a healthy diet? What changes could you make?",
      "Do you drink alcohol, if so are you drinking too much? Is there a way for you to cut down?",
      "How does alcohol change you as a person?",
      "Do you feel that your job is affecting your health?",
      "Do you overthink things? Does this cause stress and worry?",
      "What area of your self-care do you need to work on more?",
      "Do you have a good work/life balance?",
      "Do you get time  just for yourself?",
      "Is there something you need to give up or cut down on? Cigarettes/alcohol/caffeine? How can you take steps to do this?"
    ]
  },
  {
    "category": "Journal Prompts For Depression",
    "prompts": [
      "List 15 things (people, objects, hobbies) that make you happy.",
      "When things are tough, I want to remember…",
      "What 3 things have I achieved today?",
      "List 3 things that you love about yourself.",
      "What is your biggest failure in life and what did you learn from it?",
      "What is your greatest achievement?",
      "What is your favourite quote?",
      "If you knew you would not fail, what one thing would you do?",
      "List 3 of your triggers and ways you can deal with them.",
      "What do you wish more people knew about you and why?",
      "List 3 of your greatest qualities.",
      "What is holding you back from your current goals? Make a list and try to find ways around the obstacles.",
      "If you could spend time with anyone, living or dead, who would you choose and why?",
      "What made you happy today?",
      "What made you upset today?",
      "How would you describe yourself to a stranger?",
      "How would you describe depression?",
      "What one thing has depression taught you?",
      "When is the last time you did something nice for yourself?",
      "How can you start making changes to improve your life?",
      "Write about the happiest time in your life?",
      "List 15 things you are grateful for.",
      "What does your dream life look like?",
      "Write about a time when you selflessly helped someone.",
      "What are the top 3 stressors causing your depression?",
      "How did your anxiety and depression begin? Write about how you felt at the beginning.",
      "Write a letter to someone who causes your depression (don't worry, you don't have to send it to them).",
      "Create a morning routine filled with habits that make you happy.",
      "Brain dump all of your worries this week.",
      "Write a letter to your future self."
    ]
  }
]
